tests/__init__.py
local_code_assistant-0.0.2.dist-info/METADATA
local_code_assistant-0.0.2.dist-info/WHEEL
local_code_assistant-0.0.2.dist-info/top_level.txt
local_code_assistant-0.0.2.dist-info/RECORD
