Metadata-Version: 2.1
Name: local_code_assistant
Version: 0.0.2
Author: Allen Nghayoui
Requires-Python: >=3.12
Requires-Dist: fastapi
Requires-Dist: bcrypt
Requires-Dist: python-multipart
Requires-Dist: python-dotenv
Requires-Dist: psycopg2
Requires-Dist: psycopg2-binary
Requires-Dist: pydantic
Requires-Dist: pydantic[email]
